[{"id":"e10a0678.c58a28","type":"tab","label":"Flow 1","disabled":true,"info":""},{"id":"f7465511.eb0dc8","type":"tab","label":"Flow 2","disabled":true,"info":""},{"id":"b061988c.4594d8","type":"tab","label":"MongoDB on Cloud","disabled":true,"info":""},{"id":"f42c43fa.3aac3","type":"mongodb3","uri":"mongodb+srv://admin:admin@123@cluster0.m0ust.mongodb.net/dht11-node-red-cloud?retryWrites=true&w=majority","name":"","options":"","parallelism":"-1"},{"id":"2c88555f.0fb14a","type":"ui_base","theme":{"name":"theme-light","lightTheme":{"default":"#0094CE","baseColor":"#0094CE","baseFont":"-apple-system,BlinkMacSystemFont,Segoe UI,Roboto,Oxygen-Sans,Ubuntu,Cantarell,Helvetica Neue,sans-serif","edited":true,"reset":false},"darkTheme":{"default":"#097479","baseColor":"#097479","baseFont":"-apple-system,BlinkMacSystemFont,Segoe UI,Roboto,Oxygen-Sans,Ubuntu,Cantarell,Helvetica Neue,sans-serif","edited":false},"customTheme":{"name":"Untitled Theme 1","default":"#4B7930","baseColor":"#4B7930","baseFont":"-apple-system,BlinkMacSystemFont,Segoe UI,Roboto,Oxygen-Sans,Ubuntu,Cantarell,Helvetica Neue,sans-serif"},"themeState":{"base-color":{"default":"#0094CE","value":"#0094CE","edited":false},"page-titlebar-backgroundColor":{"value":"#0094CE","edited":false},"page-backgroundColor":{"value":"#fafafa","edited":false},"page-sidebar-backgroundColor":{"value":"#ffffff","edited":false},"group-textColor":{"value":"#1bbfff","edited":false},"group-borderColor":{"value":"#ffffff","edited":false},"group-backgroundColor":{"value":"#ffffff","edited":false},"widget-textColor":{"value":"#111111","edited":false},"widget-backgroundColor":{"value":"#0094ce","edited":false},"widget-borderColor":{"value":"#ffffff","edited":false},"base-font":{"value":"-apple-system,BlinkMacSystemFont,Segoe UI,Roboto,Oxygen-Sans,Ubuntu,Cantarell,Helvetica Neue,sans-serif"}},"angularTheme":{"primary":"indigo","accents":"blue","warn":"red","background":"grey"}},"site":{"name":"Node-RED Dashboard","hideToolbar":"false","allowSwipe":"false","lockMenu":"false","allowTempTheme":"true","dateFormat":"DD/MM/YYYY","sizes":{"sx":48,"sy":48,"gx":6,"gy":6,"cx":6,"cy":6,"px":0,"py":0}}},{"id":"7d70b34c.2e00ec","type":"ui_tab","name":"Tab 1","icon":"dashboard","order":1,"disabled":false,"hidden":false},{"id":"d82f62dc.cce7f","type":"ui_group","name":"Group 1","tab":"7d70b34c.2e00ec","order":1,"disp":true,"width":6},{"id":"e2368f34.1f01a","type":"ui_group","name":"Default","tab":"7d70b34c.2e00ec","order":2,"disp":true,"width":"6","collapse":false},{"id":"1372ad38.49ba73","type":"ui_group","name":"Group 3","tab":"7d70b34c.2e00ec","order":3,"disp":true,"width":6},{"id":"f3ab29f.46641d8","type":"mqtt-broker","name":"","broker":"54.151.203.250","port":"1883","clientid":"","usetls":false,"compatmode":false,"keepalive":"60","cleansession":true,"birthTopic":"","birthQos":"0","birthPayload":"","closeTopic":"","closeQos":"0","closePayload":"","willTopic":"","willQos":"0","willPayload":""},{"id":"874d9250.a2d9a","type":"mqtt-broker","name":"","broker":"34.203.56.108","port":"1883","clientid":"","usetls":false,"compatmode":false,"keepalive":"60","cleansession":true,"birthTopic":"","birthQos":"0","birthPayload":"","closeTopic":"","closeQos":"0","closePayload":"","willTopic":"","willQos":"0","willPayload":""},{"id":"11da97cf.a9aa68","type":"ui_group","name":"Group 1","tab":"","order":1,"disp":true,"width":6},{"id":"ff86040d.ea2448","type":"ui_group","name":"Group 2","tab":"","order":2,"disp":true,"width":6},{"id":"54911200.85a2c","type":"mongodb3","uri":"mongodb://localhost:27017/node-red","name":"","options":"","parallelism":"-1"},{"id":"50901a1.5f4b3e4","type":"ui_group","name":"Group 3","tab":"","order":3,"disp":true,"width":6},{"id":"d102284f.a26708","type":"ui_group","name":"Group 1","tab":"","order":1,"disp":true,"width":6},{"id":"6e7091f4.5e6cb","type":"ui_group","name":"Group 2","tab":"","order":2,"disp":true,"width":6},{"id":"9e5bdd6d.2127f","type":"ui_group","name":"Group 3","tab":"","order":3,"disp":true,"width":6},{"id":"205235c3.60ff0a","type":"mqtt-broker","name":"test","broker":"localhost","port":"1883","clientid":"","usetls":false,"compatmode":false,"keepalive":"60","cleansession":true,"birthTopic":"","birthQos":"0","birthPayload":"","closeTopic":"","closeQos":"0","closePayload":"","willTopic":"","willQos":"0","willPayload":""},{"id":"470ba21f.9fe31c","type":"mqtt-broker","name":"","broker":"34.203.56.108","port":"1883","clientid":"","usetls":false,"compatmode":false,"keepalive":"60","cleansession":true,"birthTopic":"","birthQos":"0","birthPayload":"","closeTopic":"","closeQos":"0","closePayload":"","willTopic":"","willQos":"0","willPayload":""},{"id":"67565cb5.bd7554","type":"ui_group","name":"Group 1","tab":"","order":1,"disp":true,"width":6},{"id":"a8ed4d7f.d8cb6","type":"ui_group","name":"Group 2","tab":"","order":2,"disp":true,"width":6},{"id":"77bf1f54.afbc5","type":"MySQLdatabase","name":"","host":"127.0.0.1","port":"3306","db":"sensors","tz":""},{"id":"6681f51e.14adcc","type":"ui_group","name":"Group 3","tab":"","order":3,"disp":true,"width":6},{"id":"8418b5ea.481368","type":"mongodb3","uri":"mongodb+srv://tangmo:tangmo_254127@cluster0.xbbiz.mongodb.net/tempc-humid","name":"showTempc","options":"","parallelism":"-1"},{"id":"7456503c.2253d","type":"ui_group","name":"Group 3","tab":"","order":3,"disp":true,"width":6},{"id":"a597f1df.efee1","type":"mongodb-var","uri":"mongodb://localhost:27017/node-red-temp","name":"show","options":"","parallelism":"-1"},{"id":"d01ed501.131cd8","type":"ui_group","name":"Group 4","tab":"","order":4,"disp":true,"width":6},{"id":"55cd5c68.d82574","type":"ui_group","name":"Group 4","tab":"7d70b34c.2e00ec","order":4,"disp":true,"width":6},{"id":"76ff7a23.92f754","type":"ui_group","name":"Group 5","tab":"7d70b34c.2e00ec","order":5,"disp":true,"width":6},{"id":"6a298e77.1b83","type":"ui_tab","name":"Tab 1","icon":"dashboard","order":1},{"id":"85d1d402.0bb388","type":"mongodb3 in","z":"e10a0678.c58a28","service":"_ext_","configNode":"f42c43fa.3aac3","name":"findToArray","collection":"products","operation":"find.toArray","x":450,"y":120,"wires":[["c0c140a8.682ca","c069cc06.d42d8","5dfadcc.2200b24"]]},{"id":"ff5c68d1.061648","type":"inject","z":"e10a0678.c58a28","name":"","props":[{"p":"payload"},{"p":"topic","vt":"str"}],"repeat":"","crontab":"","once":false,"onceDelay":0.1,"topic":"","payload":"","payloadType":"date","x":180,"y":120,"wires":[["85d1d402.0bb388"]]},{"id":"c0c140a8.682ca","type":"debug","z":"e10a0678.c58a28","name":"","active":true,"tosidebar":true,"console":false,"tostatus":false,"complete":"false","statusVal":"","statusType":"auto","x":710,"y":120,"wires":[]},{"id":"c069cc06.d42d8","type":"ui_template","z":"e10a0678.c58a28","group":"d82f62dc.cce7f","name":"","order":0,"width":"0","height":"0","format":"<ul>\n  <li ng-repeat=\"item in msg.payload\">{{item._id}}</li> \n</ul> ","storeOutMessages":true,"fwdInMessages":true,"resendOnRefresh":true,"templateScope":"local","x":700,"y":200,"wires":[[]]},{"id":"bb9d6ea7.55cf9","type":"inject","z":"e10a0678.c58a28","name":"","props":[{"p":"payload"},{"p":"topic","vt":"str"}],"repeat":"","crontab":"","once":false,"onceDelay":0.1,"topic":"","payload":"hello james","payloadType":"str","x":190,"y":200,"wires":[[]]},{"id":"5dfadcc.2200b24","type":"ui_template","z":"e10a0678.c58a28","group":"e2368f34.1f01a","name":"","order":1,"width":"6","height":"8","format":"<!DOCTYPE html>\n<html lang=\"en\">\n<head> \n  <meta charset=\"utf-8\">\n  <meta name=\"viewport\" content=\"width=device-width, initial-scale=1\">\n  <link rel=\"stylesheet\" href=\"https://maxcdn.bootstrapcdn.com/bootstrap/4.5.2/css/bootstrap.min.css\">\n  <script src=\"https://ajax.googleapis.com/ajax/libs/jquery/3.5.1/jquery.min.js\"></script>\n  <script src=\"https://cdnjs.cloudflare.com/ajax/libs/popper.js/1.16.0/umd/popper.min.js\"></script>\n  <script src=\"https://maxcdn.bootstrapcdn.com/bootstrap/4.5.2/js/bootstrap.min.js\"></script>\n</head>\n<body>\n\n<div class=\"container\">\n  <h2>Product</h2>            \n  <table class=\"table\">\n    <thead>\n      <tr>\n        <th>#</th> \n        <th>Name</th>\n        <th>Category</th>\n        <th>Price</th>\n      </tr>\n    </thead>\n    <tbody>\n      <tr ng-repeat=\"item in msg.payload\">\n        <td>{{$index + 1}}</td>\n        <td>{{item.name}}</td>\n        <td>{{item.category}}</td>\n        <td>{{item.price}}</td>\n      </tr>\n    </tbody>\n  </table>\n</div>\n\n</body>\n</html>\n","storeOutMessages":true,"fwdInMessages":true,"resendOnRefresh":true,"templateScope":"local","x":700,"y":280,"wires":[[]]},{"id":"dba922ab.00795","type":"inject","z":"f7465511.eb0dc8","name":"","props":[{"p":"payload"},{"p":"key2","v":"36","vt":"str"}],"repeat":"","crontab":"","once":false,"onceDelay":0.1,"topic":"","payload":"78","payloadType":"str","x":150,"y":120,"wires":[["21eeb48c.02690c"]]},{"id":"1ad752d4.9d8c1d","type":"mongodb3 in","z":"f7465511.eb0dc8","service":"_ext_","configNode":"f42c43fa.3aac3","name":"saveData","collection":"node1","operation":"save","x":600,"y":120,"wires":[["be28f85e.c126b8"]]},{"id":"21eeb48c.02690c","type":"function","z":"f7465511.eb0dc8","name":"convertObjFucn","func":"//ค่าที่ได้รับ\nconst data1 = msg.payload;\nconst key2 = msg.key2;\n\nconst obj = { \n    \"data\": data1,\n    \"key2\": key2\n}\n\nmsg.payload = obj;\n\nreturn msg;","outputs":1,"noerr":0,"initialize":"","finalize":"","x":360,"y":120,"wires":[["1ad752d4.9d8c1d"]]},{"id":"be28f85e.c126b8","type":"debug","z":"f7465511.eb0dc8","name":"","active":true,"tosidebar":true,"console":false,"tostatus":false,"complete":"false","statusVal":"","statusType":"auto","x":830,"y":120,"wires":[]},{"id":"e57fa7bb.d6d498","type":"mongodb3 in","z":"f7465511.eb0dc8","service":"_ext_","configNode":"f42c43fa.3aac3","name":"findData","collection":"node1","operation":"find.toArray","x":580,"y":240,"wires":[["14ff9a5d.9eeca6"]]},{"id":"14ff9a5d.9eeca6","type":"debug","z":"f7465511.eb0dc8","name":"","active":true,"tosidebar":true,"console":false,"tostatus":false,"complete":"false","statusVal":"","statusType":"auto","x":810,"y":240,"wires":[]},{"id":"1ca6cfaf.e526b","type":"inject","z":"f7465511.eb0dc8","name":"","props":[{"p":"payload"},{"p":"topic","vt":"str"}],"repeat":"","crontab":"","once":false,"onceDelay":0.1,"topic":"","payload":"","payloadType":"date","x":360,"y":240,"wires":[["e57fa7bb.d6d498"]]},{"id":"c2af0807.480558","type":"mqtt in","z":"f7465511.eb0dc8","name":"","topic":"humid","qos":"2","datatype":"auto","broker":"f3ab29f.46641d8","x":110,"y":360,"wires":[["b3542083.e655c"]]},{"id":"c7b998cc.b87a08","type":"mqtt in","z":"f7465511.eb0dc8","name":"","topic":"tempc","qos":"2","datatype":"auto","broker":"f3ab29f.46641d8","x":110,"y":440,"wires":[["b3542083.e655c"]]},{"id":"b3542083.e655c","type":"join","z":"f7465511.eb0dc8","name":"","mode":"custom","build":"object","property":"payload","propertyType":"msg","key":"topic","joiner":"\\n","joinerType":"str","accumulate":true,"timeout":"","count":"2","reduceRight":false,"reduceExp":"","reduceInit":"","reduceInitType":"","reduceFixup":"","x":290,"y":400,"wires":[["6d4a4732.8f9568"]]},{"id":"8ff5e2e5.0a7cd","type":"mongodb3 in","z":"f7465511.eb0dc8","service":"_ext_","configNode":"f42c43fa.3aac3","name":"saveDataDht11","collection":"dht11-node1","operation":"save","x":740,"y":400,"wires":[[]]},{"id":"6d4a4732.8f9568","type":"function","z":"f7465511.eb0dc8","name":"","func":"const humid = msg.payload.humid;\nconst tempc = msg.payload.tempc;\n \nconst d = new Date();\nconst timerecord =  d.toString();\n\nconst jsonPayload = {\n    \"tempc\":tempc,\n    \"humid\":humid,\n    \"timerecord\":timerecord\n};\n\nmsg.payload = jsonPayload;\n\nreturn msg;","outputs":1,"noerr":0,"initialize":"","finalize":"","x":480,"y":400,"wires":[["8ff5e2e5.0a7cd"]]},{"id":"d7e36cc5.b4802","type":"inject","z":"f7465511.eb0dc8","name":"","props":[{"p":"payload"},{"p":"topic","vt":"str"}],"repeat":"","crontab":"","once":false,"onceDelay":0.1,"topic":"","payload":"","payloadType":"date","x":160,"y":560,"wires":[["fbce882f.753108"]]},{"id":"fbce882f.753108","type":"mongodb3 in","z":"f7465511.eb0dc8","service":"_ext_","configNode":"f42c43fa.3aac3","name":"findDHT11Data","collection":"dht11-node1","operation":"find.toArray","x":440,"y":560,"wires":[["8aa377c7.b588e8","73ff1f51.06cc6"]]},{"id":"8aa377c7.b588e8","type":"debug","z":"f7465511.eb0dc8","name":"","active":true,"tosidebar":true,"console":false,"tostatus":false,"complete":"false","statusVal":"","statusType":"auto","x":760,"y":560,"wires":[]},{"id":"73ff1f51.06cc6","type":"ui_template","z":"f7465511.eb0dc8","group":"55cd5c68.d82574","name":"","order":0,"width":"6","height":"10","format":"<!DOCTYPE html>\n<html lang=\"en\">\n<head> \n  <meta charset=\"utf-8\">\n  <meta name=\"viewport\" content=\"width=device-width, initial-scale=1\">\n  <link rel=\"stylesheet\" href=\"https://maxcdn.bootstrapcdn.com/bootstrap/4.5.2/css/bootstrap.min.css\">\n  <script src=\"https://ajax.googleapis.com/ajax/libs/jquery/3.5.1/jquery.min.js\"></script>\n  <script src=\"https://cdnjs.cloudflare.com/ajax/libs/popper.js/1.16.0/umd/popper.min.js\"></script>\n  <script src=\"https://maxcdn.bootstrapcdn.com/bootstrap/4.5.2/js/bootstrap.min.js\"></script>\n</head>\n<body>\n\n<div class=\"container\">\n  <h2>DHT11 Data</h2>            \n  <table class=\"table\">\n    <thead>\n      <tr>\n        <th>#</th> \n        <th>humid</th>\n        <th>tempc</th> \n        <th>timerecord</th>\n      </tr>\n    </thead>\n    <tbody>\n      <tr ng-repeat=\"item in msg.payload\">\n        <td>{{$index + 1}}</td>\n        <td>{{item.humid}}</td>\n        <td>{{item.tempc}}</td> \n        <td>{{item.timerecord}}</td> \n      </tr>\n    </tbody>\n  </table>\n</div>\n\n</body>\n</html>\n","storeOutMessages":true,"fwdInMessages":true,"resendOnRefresh":true,"templateScope":"local","x":760,"y":660,"wires":[[]]},{"id":"f3b72236.e7717","type":"inject","z":"b061988c.4594d8","name":"","props":[{"p":"payload"},{"p":"topic","vt":"str"}],"repeat":"","crontab":"","once":false,"onceDelay":0.1,"topic":"","payload":"{\"id\":2,\"name\":\"Admin James\"}","payloadType":"json","x":160,"y":140,"wires":[["c977eeab.71c3"]]},{"id":"c977eeab.71c3","type":"mongodb3 in","z":"b061988c.4594d8","service":"_ext_","configNode":"f42c43fa.3aac3","name":"saveOnCloud","collection":"test-atlas","operation":"save","x":450,"y":140,"wires":[["9eb6c7e3.459a18"]]},{"id":"9eb6c7e3.459a18","type":"debug","z":"b061988c.4594d8","name":"","active":true,"tosidebar":true,"console":false,"tostatus":false,"complete":"false","statusVal":"","statusType":"auto","x":740,"y":140,"wires":[]},{"id":"80cd5e0c.4d8bb","type":"inject","z":"b061988c.4594d8","name":"","props":[{"p":"payload"},{"p":"topic","vt":"str"}],"repeat":"","crontab":"","once":false,"onceDelay":0.1,"topic":"","payload":"","payloadType":"date","x":160,"y":300,"wires":[["deb1f4c1.758888"]]},{"id":"125dfada.23cd65","type":"debug","z":"b061988c.4594d8","name":"","active":true,"tosidebar":true,"console":false,"tostatus":false,"complete":"false","statusVal":"","statusType":"auto","x":670,"y":240,"wires":[]},{"id":"deb1f4c1.758888","type":"mongodb3 in","z":"b061988c.4594d8","service":"_ext_","configNode":"f42c43fa.3aac3","name":"findToTest-atlas","collection":"test-atlas","operation":"find.toArray","x":420,"y":300,"wires":[["125dfada.23cd65","803247d7.81fb08"]]},{"id":"803247d7.81fb08","type":"ui_template","z":"b061988c.4594d8","group":"76ff7a23.92f754","name":"","order":0,"width":"6","height":"10","format":"<!DOCTYPE html>\n<html lang=\"en\">\n<head> \n  <meta charset=\"utf-8\">\n  <meta name=\"viewport\" content=\"width=device-width, initial-scale=1\">\n  <link rel=\"stylesheet\" href=\"https://maxcdn.bootstrapcdn.com/bootstrap/4.5.2/css/bootstrap.min.css\">\n  <script src=\"https://ajax.googleapis.com/ajax/libs/jquery/3.5.1/jquery.min.js\"></script>\n  <script src=\"https://cdnjs.cloudflare.com/ajax/libs/popper.js/1.16.0/umd/popper.min.js\"></script>\n  <script src=\"https://maxcdn.bootstrapcdn.com/bootstrap/4.5.2/js/bootstrap.min.js\"></script>\n</head>\n<body>\n\n<div class=\"container\">\n  <h2>DHT11 Data On Cloud</h2>            \n  <table class=\"table\">\n    <thead>\n      <tr>\n        <th>#</th> \n        <th>id</th>\n        <th>name</th>  \n      </tr>\n    </thead>\n    <tbody>\n      <tr ng-repeat=\"item in msg.payload\">\n        <td>{{$index + 1}}</td>\n        <td>{{item.id}}</td>\n        <td>{{item.name}}</td>  \n      </tr>\n    </tbody>\n  </table>\n</div>\n\n</body>\n</html>\n","storeOutMessages":true,"fwdInMessages":true,"resendOnRefresh":true,"templateScope":"local","x":660,"y":360,"wires":[[]]},{"id":"bc4bbe94.6b0c9","type":"mqtt in","z":"b061988c.4594d8","name":"","topic":"humid","qos":"2","datatype":"auto","broker":"f3ab29f.46641d8","x":130,"y":420,"wires":[["a062424c.6c5c4","d63cdfc.76cb32"]]},{"id":"3a2fe0a7.c569f","type":"mqtt in","z":"b061988c.4594d8","name":"","topic":"tempc","qos":"2","datatype":"auto","broker":"f3ab29f.46641d8","x":130,"y":520,"wires":[["a062424c.6c5c4","54e2242.d073ddc"]]},{"id":"a062424c.6c5c4","type":"join","z":"b061988c.4594d8","name":"","mode":"custom","build":"object","property":"payload","propertyType":"msg","key":"topic","joiner":"\\n","joinerType":"str","accumulate":true,"timeout":"","count":"2","reduceRight":false,"reduceExp":"","reduceInit":"","reduceInitType":"","reduceFixup":"","x":310,"y":480,"wires":[["20cc2d35.63b242"]]},{"id":"1aec0d02.28d9b3","type":"mongodb3 in","z":"b061988c.4594d8","service":"_ext_","configNode":"f42c43fa.3aac3","name":"saveDataDht11OnCloud","collection":"dht11-node1","operation":"save","x":710,"y":480,"wires":[[]]},{"id":"20cc2d35.63b242","type":"function","z":"b061988c.4594d8","name":"","func":"const humid = msg.payload.humid;\nconst tempc = msg.payload.tempc;\n \nconst d = new Date();\nconst timerecord =  d.toString();\n\nconst jsonPayload = {\n    \"tempc\":tempc,\n    \"humid\":humid,\n    \"timerecord\":timerecord\n};\n\nmsg.payload = jsonPayload;\n\nreturn msg;","outputs":1,"noerr":0,"initialize":"","finalize":"","x":460,"y":480,"wires":[[]]},{"id":"4cd4d261.f9265c","type":"debug","z":"b061988c.4594d8","name":"","active":true,"tosidebar":true,"console":false,"tostatus":false,"complete":"false","statusVal":"","statusType":"auto","x":670,"y":560,"wires":[]},{"id":"39b00c6e.3950a4","type":"inject","z":"b061988c.4594d8","name":"","props":[{"p":"payload"},{"p":"topic","vt":"str"}],"repeat":"","crontab":"","once":false,"onceDelay":0.1,"topic":"","payload":"","payloadType":"date","x":120,"y":760,"wires":[["36d514ab.a9655c"]]},{"id":"36d514ab.a9655c","type":"mongodb3 in","z":"b061988c.4594d8","service":"_ext_","configNode":"f42c43fa.3aac3","name":"findDHT11DataOnCLoud","collection":"dht11-node1","operation":"find.toArray","x":450,"y":760,"wires":[["5e18fea3.9daab","e0182311.cbe2b"]]},{"id":"5e18fea3.9daab","type":"debug","z":"b061988c.4594d8","name":"","active":true,"tosidebar":true,"console":false,"tostatus":false,"complete":"false","statusVal":"","statusType":"auto","x":770,"y":800,"wires":[]},{"id":"e0182311.cbe2b","type":"ui_template","z":"b061988c.4594d8","group":"55cd5c68.d82574","name":"","order":0,"width":"6","height":"10","format":"<!DOCTYPE html>\n<html lang=\"en\">\n<head> \n  <meta charset=\"utf-8\">\n  <meta name=\"viewport\" content=\"width=device-width, initial-scale=1\">\n  <link rel=\"stylesheet\" href=\"https://maxcdn.bootstrapcdn.com/bootstrap/4.5.2/css/bootstrap.min.css\">\n  <script src=\"https://ajax.googleapis.com/ajax/libs/jquery/3.5.1/jquery.min.js\"></script>\n  <script src=\"https://cdnjs.cloudflare.com/ajax/libs/popper.js/1.16.0/umd/popper.min.js\"></script>\n  <script src=\"https://maxcdn.bootstrapcdn.com/bootstrap/4.5.2/js/bootstrap.min.js\"></script>\n</head>\n<body>\n\n<div class=\"container\">\n  <h2>DHT11 Data On cloud</h2>            \n  <table class=\"table\">\n    <thead>\n      <tr>\n        <th>#</th> \n        <th>humid</th>\n        <th>tempc</th> \n        <th>timerecord</th>\n      </tr>\n    </thead>\n    <tbody>\n      <tr ng-repeat=\"item in msg.payload\">\n        <td>{{$index + 1}}</td>\n        <td>{{item.humid}}</td>\n        <td>{{item.tempc}}</td> \n        <td>{{item.timerecord}}</td> \n      </tr>\n    </tbody>\n  </table>\n</div>\n\n</body>\n</html>\n","storeOutMessages":true,"fwdInMessages":true,"resendOnRefresh":true,"templateScope":"local","x":760,"y":720,"wires":[[]]},{"id":"d63cdfc.76cb32","type":"debug","z":"b061988c.4594d8","name":"","active":true,"tosidebar":true,"console":false,"tostatus":false,"complete":"false","statusVal":"","statusType":"auto","x":370,"y":560,"wires":[]},{"id":"54e2242.d073ddc","type":"debug","z":"b061988c.4594d8","name":"","active":true,"tosidebar":true,"console":false,"tostatus":false,"complete":"false","statusVal":"","statusType":"auto","x":370,"y":640,"wires":[]}]